odbc_niceties/__init__.py
odbc_niceties-0.3.0.dist-info/WHEEL
odbc_niceties-0.3.0.dist-info/METADATA
odbc_niceties-0.3.0.dist-info/RECORD
