Metadata-Version: 2.1
Name: odbc-niceties
Version: 0.3.0
Summary: Some ODBC nice things.
Author: joefromct
Requires-Python: >=3.7,<4.0
Classifier: Programming Language :: Python :: 3
Classifier: Programming Language :: Python :: 3.7
Classifier: Programming Language :: Python :: 3.8
Requires-Dist: cytoolz
Requires-Dist: pyodbc
Requires-Dist: tabulate
